LICENSE.txt
MANIFEST.in
README.md
requirements.txt
setup.py
Hoboken.egg-info/PKG-INFO
Hoboken.egg-info/SOURCES.txt
Hoboken.egg-info/dependency_links.txt
Hoboken.egg-info/not-zip-safe
Hoboken.egg-info/requires.txt
Hoboken.egg-info/top_level.txt
hoboken/LICENSE_six.txt
hoboken/__init__.py
hoboken/_version.py
hoboken/application.py
hoboken/conditions.py
hoboken/exceptions.py
hoboken/ext.py
hoboken/helpers.py
hoboken/matchers.py
hoboken/objects.py
hoboken/six.py
hoboken/tests/__init__.py
hoboken/tests/__main__.py
hoboken/tests/helpers.py
hoboken/tests/reversing_tests.yaml
hoboken/tests/routing_tests.yaml
hoboken/tests/test_HobokenApplication.py
hoboken/tests/test_beforeafter.py
hoboken/tests/test_conditions.py
hoboken/tests/test_ext.py
hoboken/tests/test_helpers.py
hoboken/tests/test_matchers.py
hoboken/tests/test_request_response.py
hoboken/tests/test_routing.py
hoboken/tests/test_shift.bare