Metadata-Version: 1.1
Name: Hoboken
Version: 0.3.1
Summary: A Sinatra-inspired web framework for Python
Home-page: http://github.com/andrew-d/hoboken
Author: Andrew Dunham
Author-email: UNKNOWN
License: Apache
Platform: any
Classifier: Development Status :: 3 - Alpha
Classifier: Environment :: Web Environment
Classifier: Intended Audience :: Developers
Classifier: License :: OSI Approved :: Apache Software License
Classifier: Operating System :: OS Independent
Classifier: Programming Language :: Python :: 2.6
Classifier: Programming Language :: Python :: 2.7
Classifier: Programming Language :: Python :: 3.2
Classifier: Topic :: Internet :: WWW/HTTP :: Dynamic Content
Classifier: Topic :: Software Development :: Libraries :: Python Modules
